LICENSE
README.md
setup.cfg
setup.py
blusutils/__init__.py
blusutils/collections.py
blusutils/crypto.py
blusutils/errors.py
blusutils/other.py
blusutils/syntax_constructions.py
blusutils/textutils.py
blusutils.egg-info/PKG-INFO
blusutils.egg-info/SOURCES.txt
blusutils.egg-info/dependency_links.txt
blusutils.egg-info/requires.txt
blusutils.egg-info/top_level.txt